gen_vpo_sfizz_presets/__main__.py
gen_vpo_sfizz_presets-0.1.1.dist-info/LICENSE
gen_vpo_sfizz_presets-0.1.1.dist-info/METADATA
gen_vpo_sfizz_presets-0.1.1.dist-info/WHEEL
gen_vpo_sfizz_presets-0.1.1.dist-info/entry_points.txt
gen_vpo_sfizz_presets-0.1.1.dist-info/top_level.txt
gen_vpo_sfizz_presets-0.1.1.dist-info/RECORD
