Metadata-Version: 2.1
Name: gen_vpo_sfizz_presets
Version: 0.1.1
Summary: Generate LV2 presets for sfizz from Virtual Playing Orchestra SFZ files
Author-email: Tres Seaver <tseaver@burgsongs.com>
Project-URL: Repository, https://github.com/tseaver/gen_vpo_sfizz_presets
Keywords: VPO,sfizz,LV2,SFZ
Classifier: Development Status :: 3 - Alpha
Classifier: Intended Audience :: Other Audience
Classifier: Topic :: Multimedia :: Sound/Audio :: MIDI
Classifier: License :: OSI Approved :: BSD License
Classifier: Programming Language :: Python :: 3
Requires-Python: >=3.8
License-File: LICENSE
